modbo/Manager.py
modbo/__init__.py
modbo/__main__.py
modbo/development.py
modbo/init.py
modbo/initialization.py
modbo/load.py
modbo/modules_loading.py
modbo/commands/__init__.py
modbo/commands/add_module.py
modbo/commands/pack_module.py
modbo/commands/remove_module.py
modbo/components/__init__.py
modbo/components/development/DevelopmentPathsRetriever.py
modbo/components/development/__init__.py
modbo/components/production/PathsRetriever.py
modbo/components/production/__init__.py
modbo/remote/RemoteCallListener.py
modbo/remote/RemoteModuleManager.py
modbo/remote/__init__.py
modbo-0.0.1.dist-info/METADATA
modbo-0.0.1.dist-info/WHEEL
modbo-0.0.1.dist-info/top_level.txt
modbo-0.0.1.dist-info/RECORD
