Metadata-Version: 2.1
Name: modbo
Version: 0.0.1
Summary: Modbo boilerplate
Home-page: https://github.com/modbo/modbo
Author: aegroto
Author-email: aegroto@protonmail.com
License: UNKNOWN
Platform: UNKNOWN
Classifier: Programming Language :: Python :: 3
Classifier: License :: OSI Approved :: MIT License
Classifier: Operating System :: OS Independent
Requires-Python: >=3.6
